{
    "title": "ep11",
    "dialogues": [
        {
            "speaker": "说话人1",
            "time": "00:10",
            "text": "チェンジばっちりと。"
        },
        {
            "speaker": "说话人2",
            "time": "00:38",
            "text": "信じられないなら、これ以上試し。今の前にはこ。"
        },
        {
            "speaker": "说话人1",
            "time": "01:05",
            "text": "の力で。うん、言いた。"
        },
        {
            "speaker": "说话人2",
            "time": "02:15",
            "text": "わるき全然違う。"
        },
        {
            "speaker": "说话人1",
            "time": "02:43",
            "text": "はい。"
        },
        {
            "speaker": "说话人2",
            "time": "02:57",
            "text": "うん。聞いている。引き上げる。近づいた怪我を見ていた運よ。村は出て、少しだけが綺麗になった後よりも、裏切ったばっかしてくれる夢が食べたい。うん。"
        },
        {
            "speaker": "说话人1",
            "time": "04:19",
            "text": "絶対的により"
        },
        {
            "speaker": "说话人2",
            "time": "04:30",
            "text": "どうしましに帰る？仲良かったです。立花さんもアズミ人間が作り出したライダーなど治癒するといい。え、サインすることができる。あの私がみなし建設のライダーのみだ。俺たち仲間じゃないか。同じ人間じゃないか？何やってんだよ？みんなじょうたんだ。どんな感じ？おしりや俺はストレムわあーとって。"
        },
        {
            "speaker": "说话人1",
            "time": "05:52",
            "text": "も好きです。またピンピンしてます。ありがとう。"
        },
        {
            "speaker": "说话人2",
            "time": "06:02",
            "text": "ございます。冗談だよ"
        },
        {
            "speaker": "说话人1",
            "time": "06:24",
            "text": "ない、マジで。すごい見ている。2022年2月29日、11月21日から11月21日です。こんにちは。失礼します。"
        },
        {
            "speaker": "说话人2",
            "time": "07:52",
            "text": "所定人間まだか？"
        },
        {
            "speaker": "说话人1",
            "time": "08:44",
            "text": "見ている。"
        },
        {
            "speaker": "说话人2",
            "time": "08:46",
            "text": "んです。降。"
        },
        {
            "speaker": "说话人1",
            "time": "09:33",
            "text": "り。"
        },
        {
            "speaker": "说话人2",
            "time": "09:42",
            "text": "て"
        },
        {
            "speaker": "说话人1",
            "time": "09:45",
            "text": "そういう。"
        },
        {
            "speaker": "说话人2",
            "time": "09:47",
            "text": "のはそれでね。"
        },
        {
            "speaker": "说话人1",
            "time": "09:58",
            "text": "まだ今"
        },
        {
            "speaker": "说话人2",
            "time": "10:00",
            "text": "ね、小室さん急かしてるわけじゃ。よろしくお願いします。そうだね。"
        },
        {
            "speaker": "说话人1",
            "time": "10:22",
            "text": "やめて。"
        },
        {
            "speaker": "说话人2",
            "time": "10:28",
            "text": "あなた自分で初め。"
        },
        {
            "speaker": "说话人1",
            "time": "10:30",
            "text": "て見た。"
        },
        {
            "speaker": "说话人2",
            "time": "10:42",
            "text": "そうだね。え。あの植物には鎮静効果もあります。なんでやね？やつはもう俺のものだ。いるわけねえよなあ。今更こんなとこに123、4567。もっと強くなれるんだろうが、本当にお前は戦うために仮面ライダーにお前が戦う理由はただ一つ力を俺は俺の力を収入するために。その通りだ。今のお前なら、これが橘さんのことだね。分析を頼んだ知り合いの専門家がついさっき結果を散らせてきて、植物の1種です。それもすでに地球上から絶滅したものだ。1体どうしてこんな物が立ちがなくて、それを彼に聞きたくて、やっとあそこ突き止めたんだけど。ありがとう。どういたしまして。それであのー紗世子さんでしたっけ？立花さんとはどのくらいの付き合いというかえじゃないの？いいじゃん。それは何かわからないけど、あの男はこれを使ってしまうぞ。お願い、引き続き、嬉しい分析を頼んで、何か分かってて。こちらにお願いします。こんな私は立場に見てみてくれた。どうしてもここに出てくるようにしてなくて。"
        },
        {
            "speaker": "说话人1",
            "time": "13:42",
            "text": "どうして。兄ちゃ。"
        },
        {
            "speaker": "说话人2",
            "time": "14:13",
            "text": "ん。"
        },
        {
            "speaker": "说话人1",
            "time": "14:30",
            "text": "君。"
        },
        {
            "speaker": "说话人2",
            "time": "15:01",
            "text": "あんちゃん、あいつが出たものだと思ってるんです。いいんだ、兄貴。出てこい。親父11歳。あつ。あ、音楽プロデュースしてたの。最近よくテレビとか出てるし、自分とこのアーティストよりゆうになって、要するに目指したがりその通りだけどな。諦めろ。お前はギターの、いや、ミュージシャンとしての才能はない。アーティストを作る側に来い。俺と同じようにスケッチ。その、俺はお前の父親だから。ちょっとあなたはね、聞いてもらえてる要請してみようとしてしまうこと言うんです。血に暴いてくれるじゃ、分かってくれ。ね。ね、なきくん。1000葉のあなたにちゃんといい仲間がいるじゃんに。"
        },
        {
            "speaker": "说话人1",
            "time": "17:26",
            "text": "ちゃったちした？"
        },
        {
            "speaker": "说话人2",
            "time": "17:40",
            "text": "いや、しかし、立花さんも隅に置けないよね。あんな美人の恋人。しかも女医さんだし。"
        },
        {
            "speaker": "说话人1",
            "time": "17:47",
            "text": "馬鹿言ってないの。"
        },
        {
            "speaker": "说话人2",
            "time": "17:52",
            "text": "あんなに心配してくれる人がいるのに、自分でさあ。"
        },
        {
            "speaker": "说话人1",
            "time": "18:05",
            "text": "ちょっと。"
        },
        {
            "speaker": "说话人2",
            "time": "18:06",
            "text": "待って。"
        },
        {
            "speaker": "说话人1",
            "time": "18:08",
            "text": "ちょっと待って、ちょっと待って、"
        },
        {
            "speaker": "说话人2",
            "time": "18:12",
            "text": "レードがわかっちゃいます。お前は好きだったです。グレードのペンで横で面白いよね。"
        },
        {
            "speaker": "说话人1",
            "time": "19:10",
            "text": "はい、なにしてますか？"
        },
        {
            "speaker": "说话人2",
            "time": "19:46",
            "text": "お父さん。"
        },
        {
            "speaker": "说话人1",
            "time": "20:22",
            "text": "本日のセットは音楽プロデューサーの、うん、1000之瀬さんです。昨日のテーマは路上ライブについてなんですけれども、路上ライブ。"
        },
        {
            "speaker": "说话人2",
            "time": "20:30",
            "text": "あんなものはただの流行で最初にやってるやつ以外は多分全く興味がないね。発生はうまくしたけど、不便。あ、こいつをメンテして、海に出して、客は別の船から見に行く。それでそいつの周りかーって、こんでそんなの絶対始発。あれが1番大丈夫？えー父親はいいの？あいつは自分の言いなりになる握りが欲しい。だけど、兄貴言ってたよな。この世界を打ち壊したいんで。それって居場所はないってことも。俺もなってや。俺じゃないやつらが口立て替えなんて、ぶち壊して、これの俺たちだけ作り、兄貴一緒に見てよ。さあ、兄貴。"
        },
        {
            "speaker": "说话人1",
            "time": "22:21",
            "text": "うん、"
        },
        {
            "speaker": "说话人2",
            "time": "22:29",
            "text": "もちろん。人間関係者の皆さんに。"
        },
        {
            "speaker": "说话人1",
            "time": "22:42",
            "text": "聞いてみてください。"
        },
        {
            "speaker": "说话人2",
            "time": "23:00",
            "text": "ちょっと待って。"
        },
        {
            "speaker": "说话人1",
            "time": "23:01",
            "text": "ちょっと待って。"
        },
        {
            "speaker": "说话人2",
            "time": "23:19",
            "text": "ちょっと待ってください。別のアイデアと戦ってる天音。"
        },
        {
            "speaker": "说话人1",
            "time": "24:23",
            "text": "お母さんへ。はじめさん見つけた。絶対連れて帰る。心配しないで、あ、まね。"
        },
        {
            "speaker": "说话人2",
            "time": "24:34",
            "text": "うん。あなたが好きです。"
        },
        {
            "speaker": "说话人1",
            "time": "25:10",
            "text": "呼んでください。"
        },
        {
            "speaker": "说话人2",
            "time": "25:19",
            "text": "出てこないじゃん。"
        }
    ]
}