{
    "title": "ep45",
    "dialogues": [
        {
            "speaker": "说话人1",
            "time": "00:10",
            "text": "全てはあの日から始まる剣崎和馬たち。仮面ライダーの戦いは恐怖を極めた。疑惑、怒り、迷い話分かれ、裏切り数々の運命のカードが彼らに配られたいくつかの出会いがあった。それを上回る数え、切れない争いがあった。そういった試練を全て乗り越えた。しかし、今、彼らは信じていた。破壊の終わりは近い。心1体のアンデッドを封印すれば、全ては終わる。彼らの知らないところで最大の試練が目覚め、つつは切り札はどこだ？切り札は誰だ？この世界はやはり滅びに向かうのか？戦いは終わらない。運命のうねりは今、クライマックスへと加速していく"
        },
        {
            "speaker": "说话人2",
            "time": "01:15",
            "text": "アンデッドは全て滅びなければならない。生き残るのは究極のアンテッドただ1人。そして私は神の声を聞くのだ。"
        },
        {
            "speaker": "说话人3",
            "time": "01:29",
            "text": "さからみちるぎ。時々しっかり閉じ込めて、奇跡、自分だけ世界に閉じ込めて、北のように。"
        },
        {
            "speaker": "说话人2",
            "time": "02:46",
            "text": "人間の命令に従いを制御するに。"
        },
        {
            "speaker": "说话人3",
            "time": "02:48",
            "text": "はありすぎるな。神よ。"
        },
        {
            "speaker": "说话人2",
            "time": "02:52",
            "text": "あなたは53隊のアンテお作りになられた。しかし私はここに新たなアンテッドの誕生を宣言する五枚目のエース。そのカードは。"
        },
        {
            "speaker": "说话人3",
            "time": "03:15",
            "text": "まだ完全には制御できていません。"
        },
        {
            "speaker": "说话人2",
            "time": "03:17",
            "text": "いや、もう10分。この中で究極のアンテッドは誕生し進化して。"
        },
        {
            "speaker": "说话人1",
            "time": "03:28",
            "text": "どうだ？"
        },
        {
            "speaker": "说话人2",
            "time": "03:29",
            "text": "神尾、お前の作ったものではない。アンテッド、お前はその存在を認めるのか？"
        },
        {
            "speaker": "说话人4",
            "time": "04:00",
            "text": "これを渡しておこうと思って。今なら君にも使いこなせると思う。俺たちの仲間として。ありがとうございます。もう使うこともないかもしれませんね。あと言って、アンデッド残っているんだぞ。でも、奴を封印するまでは戦い終わらない。月が帰るって。もう帰るの？コーヒー入れたのに、望みが待ってるんで。そうか。お邪魔しました。"
        },
        {
            "speaker": "说话人3",
            "time": "04:41",
            "text": "気をつけてね。色々。"
        },
        {
            "speaker": "说话人2",
            "time": "04:44",
            "text": "あれ。"
        },
        {
            "speaker": "说话人4",
            "time": "04:50",
            "text": "色々ってどういう意味だって。"
        },
        {
            "speaker": "说话人5",
            "time": "04:53",
            "text": "敵はアンデッドだけじゃないみたいだから。"
        },
        {
            "speaker": "说话人4",
            "time": "04:56",
            "text": "そうか。この前倒したやつは人為的に合成されたアンデッドだったということは作ったやつがどこかにいるんだ。俺、ちょっと出かけてくる。"
        },
        {
            "speaker": "说话人5",
            "time": "05:06",
            "text": "天崎君。"
        },
        {
            "speaker": "说话人4",
            "time": "05:09",
            "text": "はい。はい、気をつけます。"
        },
        {
            "speaker": "说话人2",
            "time": "05:22",
            "text": "ご苦労様。仮面ライダー諸君。そして、さようなら。"
        },
        {
            "speaker": "说话人3",
            "time": "05:45",
            "text": "最後の羽と。不倫した時。"
        },
        {
            "speaker": "说话人4",
            "time": "05:47",
            "text": "お戦いはジョーカーが勝ち残ったことになる。いや。"
        },
        {
            "speaker": "说话人3",
            "time": "05:50",
            "text": "初めはもうジ。"
        },
        {
            "speaker": "说话人4",
            "time": "05:58",
            "text": "ョーカーの本能を乗り越えている。何も起こるはずがない。"
        },
        {
            "speaker": "说话人5",
            "time": "06:06",
            "text": "はい。どうぞ。ありがとうございます。"
        },
        {
            "speaker": "说话人3",
            "time": "06:08",
            "text": "いらっしゃい。"
        },
        {
            "speaker": "说话人5",
            "time": "06:09",
            "text": "あ、駄目よ。女の子待たしちゃ。すいません。"
        },
        {
            "speaker": "说话人4",
            "time": "06:13",
            "text": "遅かったね。ちょっと剣崎さん。"
        },
        {
            "speaker": "说话人6",
            "time": "06:14",
            "text": "に呼ばれてて。今日はデートなんだ。いいなあ。ところで、あの時、一緒にいた女性とはどうなったんですか？"
        },
        {
            "speaker": "说话人4",
            "time": "06:25",
            "text": "またその話。"
        },
        {
            "speaker": "说话人6",
            "time": "06:28",
            "text": "勘弁してよ。勘弁できないなあ。何のこと？"
        },
        {
            "speaker": "说话人5",
            "time": "06:31",
            "text": "いや。"
        },
        {
            "speaker": "说话人4",
            "time": "06:32",
            "text": "何でもない。いらっしゃい。外で話できませんか？のぞみ、ちょっと待って。話があるなら早く言え。残ったはんでと封印せずに、そのままにしておくことはできないんでしょうか？アンデッドは最後の1体になるまで戦い続ける。でも、人間アンデッドは最後の1体になるまで戦い続ける人間にも機会が及ぶでも人間を襲わないアンデートだっています。あなたや、神父さんや女じゃないわ。そういうアンデッドなら、最後の1体になるまで戦わないこともできるんじゃないですか？俺は俺が仮面ライダーでいいのかって、ずっと考えてました。そして思ったんです。アンデッドの気持ちが分かる。だから、アンデッドと手を取り合って生きていこうって。甘いな。アンデッドは人間との共存なんて望んでいない。そうかな。でも、あなただっ。"
        },
        {
            "speaker": "说话人6",
            "time": "08:37",
            "text": "て朽木。遅れるよ。"
        },
        {
            "speaker": "说话人4",
            "time": "08:42",
            "text": "うん。お前は今の楽しみ。"
        },
        {
            "speaker": "说话人3",
            "time": "09:12",
            "text": "あれ？"
        },
        {
            "speaker": "说话人4",
            "time": "09:12",
            "text": "おかしいな。すいません。もう1回だけ。"
        },
        {
            "speaker": "说话人3",
            "time": "09:24",
            "text": "あれ、"
        },
        {
            "speaker": "说话人4",
            "time": "09:45",
            "text": "何者？崎様"
        },
        {
            "speaker": "说话人3",
            "time": "09:59",
            "text": "残らんでとあとカテゴリキングだけのはず。"
        },
        {
            "speaker": "说话人4",
            "time": "10:12",
            "text": "給料が入ってない。見てくれよ。銀行の残高。27円。"
        },
        {
            "speaker": "说话人5",
            "time": "10:27",
            "text": "今まではボード名義のまま振り込まれてたんでしょう？ボードの上部組織が処理してるんだと思ってたけど。"
        },
        {
            "speaker": "说话人4",
            "time": "10:34",
            "text": "どうして？突然。"
        },
        {
            "speaker": "说话人3",
            "time": "10:38",
            "text": "健作。どうしたの？俺の中アレックス。水早く手。"
        },
        {
            "speaker": "说话人5",
            "time": "10:58",
            "text": "ごり有名なんで。"
        },
        {
            "speaker": "说话人3",
            "time": "11:05",
            "text": "ちょっと。そうか。え？なんで？"
        },
        {
            "speaker": "说话人2",
            "time": "11:09",
            "text": "全てのアンデッドを封印吸収するケルベロスの力、ジョーカーも逃げるしかないとはな。"
        },
        {
            "speaker": "说话人3",
            "time": "11:49",
            "text": "追え。顔してるってこと。"
        },
        {
            "speaker": "说话人6",
            "time": "11:52",
            "text": "は仮面ライダーの仕事でしょう？いつでもできるから。"
        },
        {
            "speaker": "说话人3",
            "time": "12:53",
            "text": "大丈夫。清水1。"
        },
        {
            "speaker": "说话人5",
            "time": "13:09",
            "text": "体は消えちゃったわ。でも、やっぱりこっちの反応はジョーカーよ。"
        },
        {
            "speaker": "说话人4",
            "time": "13:17",
            "text": "どういうこと？初めはジョーカーに戻らないはずだよね。何かの作戦か？それともそ。"
        },
        {
            "speaker": "说话人3",
            "time": "13:25",
            "text": "こへ連れてってくれ。"
        },
        {
            "speaker": "说话人5",
            "time": "13:28",
            "text": "無理よ。剣崎君。"
        },
        {
            "speaker": "说话人3",
            "time": "13:29",
            "text": "初めに何かあったんだ？"
        },
        {
            "speaker": "说话人2",
            "time": "13:52",
            "text": "死ね、なぜその姿をしている？"
        },
        {
            "speaker": "说话人3",
            "time": "13:57",
            "text": "やつの全てのカードを奪われたカ。"
        },
        {
            "speaker": "说话人4",
            "time": "13:59",
            "text": "ード奪われた。お。"
        },
        {
            "speaker": "说话人3",
            "time": "14:02",
            "text": "俺はまた長官の本能。"
        },
        {
            "speaker": "说话人2",
            "time": "14:08",
            "text": "もしもこいつが勝ち残ったら。"
        },
        {
            "speaker": "说话人3",
            "time": "14:31",
            "text": "世界は"
        },
        {
            "speaker": "说话人2",
            "time": "14:35",
            "text": "今ならこいつを封印できる。"
        },
        {
            "speaker": "说话人4",
            "time": "15:00",
            "text": "俺を封印したいのか？あの女のように俺は君と話したい話すだと。もう戦うのはやめないか？情けをかけてくれるってか？違う。"
        },
        {
            "speaker": "说话人5",
            "time": "15:23",
            "text": "その辺りのはずだけど。"
        },
        {
            "speaker": "说话人4",
            "time": "15:31",
            "text": "立花さん。剣崎。やはりお前の体両方来たから。"
        },
        {
            "speaker": "说话人3",
            "time": "15:40",
            "text": "1目目を覚ませ。一。"
        },
        {
            "speaker": "说话人4",
            "time": "15:56",
            "text": "じゃあ、これがジョークか。何者か外貨を始めのカードを全てよかった。そのために、ジョーカーの姿に戻るしかなかったこと。カテゴリー勤務ですか？"
        },
        {
            "speaker": "说话人5",
            "time": "16:08",
            "text": "違うわ。ジョーカーと戦っていたのはカテゴリー不明のアンデッドだった。"
        },
        {
            "speaker": "说话人4",
            "time": "16:13",
            "text": "でも、他にアンデッドがいるわけないじゃない。最後の1体のはずなんだから。こいつがジョーカーに戻ったことで、お前は影響を受けている。再び、もう1人の浄化になりかけてるんだ。1体誰が始めよう？俺は最近封印したアンデッドたちの声が聞こえてくるんです。仲居をやめろ。無常観も封印されることがなければ、もう何も起こらないって戦う。やめて、それでどうする？同情感も。それでどうする？仲間のクワ型虫たちと森に暮らせっていうのかい。人間と共存すれば、俺は俺たちの世界を作る。人間など1人もいない。素晴らしい世界だ。共存だと実は。"
        },
        {
            "speaker": "说话人3",
            "time": "17:39",
            "text": "危ない。"
        },
        {
            "speaker": "说话人4",
            "time": "17:43",
            "text": "お前が最後のアンデッドじゃなかったのか？人造アンデッドだ。こいつも説得してみるか。"
        },
        {
            "speaker": "说话人3",
            "time": "17:50",
            "text": "変人。"
        },
        {
            "speaker": "说话人1",
            "time": "18:06",
            "text": "ネットの細胞を合成している。"
        },
        {
            "speaker": "说话人4",
            "time": "18:09",
            "text": "逃げた方が良さそうだぜ。"
        },
        {
            "speaker": "说话人3",
            "time": "18:22",
            "text": "おいら。なんだそいつはきっとあいつが初めのカードを奪ったんだ。検査助け。"
        },
        {
            "speaker": "说话人4",
            "time": "18:40",
            "text": "て置いちゃう。"
        },
        {
            "speaker": "说话人3",
            "time": "18:59",
            "text": "新しいホームはない。"
        },
        {
            "speaker": "说话人2",
            "time": "19:03",
            "text": "良い仲間がいる。"
        },
        {
            "speaker": "说话人3",
            "time": "19:04",
            "text": "剣崎さんもらったカード。"
        },
        {
            "speaker": "说话人4",
            "time": "19:08",
            "text": "一緒に戦ってくれ。"
        },
        {
            "speaker": "说话人1",
            "time": "19:37",
            "text": "あいつ。"
        },
        {
            "speaker": "说话人2",
            "time": "19:38",
            "text": "なんでって、取り込んでしまえるんか？"
        },
        {
            "speaker": "说话人1",
            "time": "19:56",
            "text": "卯月。"
        },
        {
            "speaker": "说话人4",
            "time": "20:01",
            "text": "やはりあいつはカテゴリーキングじゃあり。"
        },
        {
            "speaker": "说话人2",
            "time": "20:03",
            "text": "ません。なんだと？"
        },
        {
            "speaker": "说话人4",
            "time": "20:05",
            "text": "じゃ、1体行くぞ。"
        },
        {
            "speaker": "说话人2",
            "time": "20:07",
            "text": "はい。無駄なことはやめた方がいい。天王寺理事長。なぜあなたが全ては計画通りだよ。トライアルシリーズのティターンケルベルスを生み出すための実験に過ぎなかったのだ。"
        },
        {
            "speaker": "说话人4",
            "time": "20:36",
            "text": "あなたがあのアンデッドを作っ。"
        },
        {
            "speaker": "说话人3",
            "time": "20:37",
            "text": "た奴を止めろ。やめさせろ。"
        },
        {
            "speaker": "说话人2",
            "time": "20:42",
            "text": "ケルベロスは誰にも止められない。違う。"
        },
        {
            "speaker": "说话人4",
            "time": "21:18",
            "text": "橘さんの角が。兄貴様。"
        },
        {
            "speaker": "说话人3",
            "time": "21:45",
            "text": "が始めろ、ガードモン。今お前は。"
        },
        {
            "speaker": "说话人4",
            "time": "21:48",
            "text": "ジョーカーの影響を受けている。ここで金庫ホームになれば。"
        },
        {
            "speaker": "说话人3",
            "time": "22:01",
            "text": "あの時のように。俺は。"
        },
        {
            "speaker": "说话人2",
            "time": "22:19",
            "text": "俺は始めの。"
        },
        {
            "speaker": "说话人4",
            "time": "22:29",
            "text": "月のカードを返し。"
        },
        {
            "speaker": "说话人3",
            "time": "22:32",
            "text": "てもらう。竜崎。"
        },
        {
            "speaker": "说话人2",
            "time": "22:59",
            "text": "君たちではケルベロスに勝つことはできない。全てのアンテッドのデータを融合させた究極のアンテッドだ。ジョーカーさえも凌ぐ、すぐに封印してやる。ジョーカーもな。"
        },
        {
            "speaker": "说话人3",
            "time": "23:23",
            "text": "そんなことはさせない。始まるんだ。これ以上誰も傷つけさせはしない。"
        },
        {
            "speaker": "说话人1",
            "time": "24:27",
            "text": "仮面ライダーブレイドジョー。"
        },
        {
            "speaker": "说话人2",
            "time": "24:28",
            "text": "カーを封印するのは俺だ。変身。"
        },
        {
            "speaker": "说话人3",
            "time": "24:31",
            "text": "お前がバトルファイトの消費者になった時、何夢がある。無論平和だ。実現させようぜ。君の望んでいた。平和ってやつ"
        }
    ]
}